typescore/__init__.py
typescore/__main__.py
typescore/typescore.py
typescore-0.11.dist-info/entry_points.txt
typescore-0.11.dist-info/LICENSE
typescore-0.11.dist-info/WHEEL
typescore-0.11.dist-info/METADATA
typescore-0.11.dist-info/RECORD
