Metadata-Version: 2.1
Name: typescore
Version: 0.11
Summary: typescore - generate typing completeness scores (and more) for a set of packages
Author-email: Graham Wheeler <graham@grahamwheeler.com>
Classifier: Intended Audience :: Developers
Classifier: License :: OSI Approved :: MIT License
Classifier: Programming Language :: Python :: 3
Classifier: Topic :: Software Development :: Quality Assurance
Requires-Dist: flit_core >=3.7
Requires-Dist: docopt
Requires-Dist: importlib-metadata
Requires-Dist: pyright
Requires-Dist: requests
Project-URL: Source, https://github.com/gramster/typescore
